art_showcase/__init__.py
art_showcase/__main__.py
art_showcase/showcase.py
art_showcase-0.0.4.dist-info/licenses/LICENSE
art_showcase-0.0.4.dist-info/METADATA
art_showcase-0.0.4.dist-info/WHEEL
art_showcase-0.0.4.dist-info/top_level.txt
art_showcase-0.0.4.dist-info/RECORD
