Metadata-Version: 2.4
Name: art_showcase
Version: 0.0.4
Summary: A simple library for custom showcasing of fonts from the 'art' PyPi package , it is helpful when trying to choose a font 
Home-page: https://github.com/victhepythonista/art-showcase
Author: Victor Kipkemboi
Author-email: scriptilapia@gmail.com
Project-URL: Bug Tracker, https://github.com/victhepythonista/art-showcase/issues
Classifier: Programming Language :: Python :: 3
Classifier: License :: OSI Approved :: MIT License
Requires-Python: >=3.6
License-File: LICENSE
Dynamic: author
Dynamic: author-email
Dynamic: classifier
Dynamic: description
Dynamic: description-content-type
Dynamic: home-page
Dynamic: license-file
Dynamic: project-url
Dynamic: requires-python
Dynamic: summary
